saladpy/__init__.py
saladpy/client.py
saladpy/exceptions.py
saladpy/methods/User.py
saladpy/methods/__init__.py
saladpy/methods/types/BaseClient.py
saladpy/methods/types/UserTypes.py
saladpy/methods/types/__init__.py
saladpy-1.0.2a5.dist-info/LICENSE
saladpy-1.0.2a5.dist-info/METADATA
saladpy-1.0.2a5.dist-info/WHEEL
saladpy-1.0.2a5.dist-info/top_level.txt
saladpy-1.0.2a5.dist-info/RECORD
