Metadata-Version: 2.1
Name: saladpy
Version: 1.0.2a5
Summary: A Python wrapper for the Salad Web API
Home-page: https://github.com/Coddo-Python/SaladPy
Author: Coddo-Python
Author-email: Coddo <coddobusiness@gmail.com>
License: The MIT License (MIT)
Project-URL: Homepage, https://github.com/Coddo-Python/SaladPy
Keywords: salad,api,salad-web-api
Classifier: License :: OSI Approved :: MIT License
Classifier: Programming Language :: Python
Classifier: Programming Language :: Python :: 3
Requires-Python: >=3.8.0
License-File: LICENSE
Requires-Dist: aiohttp (<4,>=3.7.4)
